{
  "A1-001": [
    "Bulbasaur",
    "Common"
  ],
  "A1-002": [
    "Ivysaur",
    "Uncommon"
  ],
  "A1-003": [
    "Venusaur",
    "Rare"
  ],
  "A1-004": [
    "Venusaur ex",
    "Double Rare"
  ],
  "A1-005": [
    "Caterpie",
    "Common"
  ],
  "A1-006": [
    "Metapod",
    "Common"
  ],
  "A1-007": [
    "Butterfree",
    "Rare"
  ],
  "A1-008": [
    "Weedle",
    "Common"
  ],
  "A1-009": [
    "Kakuna",
    "Common"
  ],
  "A1-010": [
    "Beedrill",
    "Rare"
  ],
  "A1-011": [
    "Oddish",
    "Common"
  ],
  "A1-012": [
    "Gloom",
    "Uncommon"
  ],
  "A1-013": [
    "Vileplume",
    "Rare"
  ],
  "A1-014": [
    "Paras",
    "Common"
  ],
  "A1-015": [
    "Parasect",
    "Uncommon"
  ],
  "A1-016": [
    "Venonat",
    "Common"
  ],
  "A1-017": [
    "Venomoth",
    "Uncommon"
  ],
  "A1-018": [
    "Bellsprout",
    "Common"
  ],
  "A1-019": [
    "Weepinbell",
    "Uncommon"
  ],
  "A1-020": [
    "Victreebel",
    "Rare"
  ],
  "A1-021": [
    "Exeggcute",
    "Common"
  ],
  "A1-022": [
    "Exeggutor",
    "Rare"
  ],
  "A1-023": [
    "Exeggutor ex",
    "Double Rare"
  ],
  "A1-024": [
    "Tangela",
    "Common"
  ],
  "A1-025": [
    "Scyther",
    "Common"
  ],
  "A1-026": [
    "Pinsir",
    "Uncommon"
  ],
  "A1-027": [
    "Cottonee",
    "Common"
  ],
  "A1-028": [
    "Whimsicott",
    "Uncommon"
  ],
  "A1-029": [
    "Petilil",
    "Common"
  ],
  "A1-030": [
    "Lilligant",
    "Uncommon"
  ],
  "A1-031": [
    "Skiddo",
    "Common"
  ],
  "A1-032": [
    "Gogoat",
    "Common"
  ],
  "A1-033": [
    "Charmander",
    "Common"
  ],
  "A1-034": [
    "Charmeleon",
    "Uncommon"
  ],
  "A1-035": [
    "Charizard",
    "Rare"
  ],
  "A1-036": [
    "Charizard ex",
    "Double Rare"
  ],
  "A1-037": [
    "Vulpix",
    "Common"
  ],
  "A1-038": [
    "Ninetales",
    "Uncommon"
  ],
  "A1-039": [
    "Growlithe",
    "Common"
  ],
  "A1-040": [
    "Arcanine",
    "Rare"
  ],
  "A1-041": [
    "Arcanine ex",
    "Double Rare"
  ],
  "A1-042": [
    "Ponyta",
    "Common"
  ],
  "A1-043": [
    "Rapidash",
    "Uncommon"
  ],
  "A1-044": [
    "Magmar",
    "Common"
  ],
  "A1-045": [
    "Flareon",
    "Rare"
  ],
  "A1-046": [
    "Moltres",
    "Rare"
  ],
  "A1-047": [
    "Moltres ex",
    "Double Rare"
  ],
  "A1-048": [
    "Heatmor",
    "Common"
  ],
  "A1-049": [
    "Salandit",
    "Common"
  ],
  "A1-050": [
    "Salazzle",
    "Common"
  ],
  "A1-051": [
    "Sizzlipede",
    "Common"
  ],
  "A1-052": [
    "Centiskorch",
    "Uncommon"
  ],
  "A1-053": [
    "Squirtle",
    "Common"
  ],
  "A1-054": [
    "Wartortle",
    "Uncommon"
  ],
  "A1-055": [
    "Blastoise",
    "Rare"
  ],
  "A1-056": [
    "Blastoise ex",
    "Double Rare"
  ],
  "A1-057": [
    "Psyduck",
    "Common"
  ],
  "A1-058": [
    "Golduck",
    "Uncommon"
  ],
  "A1-059": [
    "Poliwag",
    "Common"
  ],
  "A1-060": [
    "Poliwhirl",
    "Uncommon"
  ],
  "A1-061": [
    "Poliwrath",
    "Rare"
  ],
  "A1-062": [
    "Tentacool",
    "Common"
  ],
  "A1-063": [
    "Tentacruel",
    "Uncommon"
  ],
  "A1-064": [
    "Seel",
    "Common"
  ],
  "A1-065": [
    "Dewgong",
    "Uncommon"
  ],
  "A1-066": [
    "Shellder",
    "Common"
  ],
  "A1-067": [
    "Cloyster",
    "Uncommon"
  ],
  "A1-068": [
    "Krabby",
    "Common"
  ],
  "A1-069": [
    "Kingler",
    "Uncommon"
  ],
  "A1-070": [
    "Horsea",
    "Common"
  ],
  "A1-071": [
    "Seadra",
    "Uncommon"
  ],
  "A1-072": [
    "Goldeen",
    "Common"
  ],
  "A1-073": [
    "Seaking",
    "Common"
  ],
  "A1-074": [
    "Staryu",
    "Common"
  ],
  "A1-075": [
    "Starmie",
    "Uncommon"
  ],
  "A1-076": [
    "Starmie ex",
    "Double Rare"
  ],
  "A1-077": [
    "Magikarp",
    "Common"
  ],
  "A1-078": [
    "Gyarados",
    "Rare"
  ],
  "A1-079": [
    "Lapras",
    "Rare"
  ],
  "A1-080": [
    "Vaporeon",
    "Rare"
  ],
  "A1-081": [
    "Omanyte",
    "Uncommon"
  ],
  "A1-082": [
    "Omastar",
    "Rare"
  ],
  "A1-083": [
    "Articuno",
    "Rare"
  ],
  "A1-084": [
    "Articuno ex",
    "Double Rare"
  ],
  "A1-085": [
    "Ducklett",
    "Common"
  ],
  "A1-086": [
    "Swanna",
    "Uncommon"
  ],
  "A1-087": [
    "Froakie",
    "Common"
  ],
  "A1-088": [
    "Frogadier",
    "Uncommon"
  ],
  "A1-089": [
    "Greninja",
    "Rare"
  ],
  "A1-090": [
    "Pyukumuku",
    "Common"
  ],
  "A1-091": [
    "Bruxish",
    "Uncommon"
  ],
  "A1-092": [
    "Snom",
    "Common"
  ],
  "A1-093": [
    "Frosmoth",
    "Uncommon"
  ],
  "A1-094": [
    "Pikachu",
    "Common"
  ],
  "A1-095": [
    "Raichu",
    "Rare"
  ],
  "A1-096": [
    "Pikachu ex",
    "Double Rare"
  ],
  "A1-097": [
    "Magnemite",
    "Common"
  ],
  "A1-098": [
    "Magneton",
    "Rare"
  ],
  "A1-099": [
    "Voltorb",
    "Common"
  ],
  "A1-100": [
    "Electrode",
    "Uncommon"
  ],
  "A1-101": [
    "Electabuzz",
    "Common"
  ],
  "A1-102": [
    "Jolteon",
    "Rare"
  ],
  "A1-103": [
    "Zapdos",
    "Rare"
  ],
  "A1-104": [
    "Zapdos ex",
    "Double Rare"
  ],
  "A1-105": [
    "Blitzle",
    "Common"
  ],
  "A1-106": [
    "Zebstrika",
    "Uncommon"
  ],
  "A1-107": [
    "Tynamo",
    "Common"
  ],
  "A1-108": [
    "Eelektrik",
    "Uncommon"
  ],
  "A1-109": [
    "Eelektross",
    "Rare"
  ],
  "A1-110": [
    "Helioptile",
    "Common"
  ],
  "A1-111": [
    "Heliolisk",
    "Common"
  ],
  "A1-112": [
    "Pincurchin",
    "Uncommon"
  ],
  "A1-113": [
    "Clefairy",
    "Common"
  ],
  "A1-114": [
    "Clefable",
    "Uncommon"
  ],
  "A1-115": [
    "Abra",
    "Common"
  ],
  "A1-116": [
    "Kadabra",
    "Uncommon"
  ],
  "A1-117": [
    "Alakazam",
    "Rare"
  ],
  "A1-118": [
    "Slowpoke",
    "Common"
  ],
  "A1-119": [
    "Slowbro",
    "Uncommon"
  ],
  "A1-120": [
    "Gastly",
    "Common"
  ],
  "A1-121": [
    "Haunter",
    "Uncommon"
  ],
  "A1-122": [
    "Gengar",
    "Rare"
  ],
  "A1-123": [
    "Gengar ex",
    "Double Rare"
  ],
  "A1-124": [
    "Drowzee",
    "Common"
  ],
  "A1-125": [
    "Hypno",
    "Rare"
  ],
  "A1-126": [
    "Mr. Mime",
    "Uncommon"
  ],
  "A1-127": [
    "Jynx",
    "Common"
  ],
  "A1-128": [
    "Mewtwo",
    "Rare"
  ],
  "A1-129": [
    "Mewtwo ex",
    "Double Rare"
  ],
  "A1-130": [
    "Ralts",
    "Common"
  ],
  "A1-131": [
    "Kirlia",
    "Uncommon"
  ],
  "A1-132": [
    "Gardevoir",
    "Rare"
  ],
  "A1-133": [
    "Woobat",
    "Common"
  ],
  "A1-134": [
    "Swoobat",
    "Common"
  ],
  "A1-135": [
    "Golett",
    "Common"
  ],
  "A1-136": [
    "Golurk",
    "Uncommon"
  ],
  "A1-137": [
    "Sandshrew",
    "Common"
  ],
  "A1-138": [
    "Sandslash",
    "Uncommon"
  ],
  "A1-139": [
    "Diglett",
    "Common"
  ],
  "A1-140": [
    "Dugtrio",
    "Uncommon"
  ],
  "A1-141": [
    "Mankey",
    "Common"
  ],
  "A1-142": [
    "Primeape",
    "Uncommon"
  ],
  "A1-143": [
    "Machop",
    "Common"
  ],
  "A1-144": [
    "Machoke",
    "Uncommon"
  ],
  "A1-145": [
    "Machamp",
    "Rare"
  ],
  "A1-146": [
    "Machamp ex",
    "Double Rare"
  ],
  "A1-147": [
    "Geodude",
    "Common"
  ],
  "A1-148": [
    "Graveler",
    "Uncommon"
  ],
  "A1-149": [
    "Golem",
    "Rare"
  ],
  "A1-150": [
    "Onix",
    "Uncommon"
  ],
  "A1-151": [
    "Cubone",
    "Common"
  ],
  "A1-152": [
    "Marowak",
    "Uncommon"
  ],
  "A1-153": [
    "Marowak ex",
    "Double Rare"
  ],
  "A1-154": [
    "Hitmonlee",
    "Common"
  ],
  "A1-155": [
    "Hitmonchan",
    "Common"
  ],
  "A1-156": [
    "Rhyhorn",
    "Common"
  ],
  "A1-157": [
    "Rhydon",
    "Uncommon"
  ],
  "A1-158": [
    "Kabuto",
    "Uncommon"
  ],
  "A1-159": [
    "Kabutops",
    "Rare"
  ],
  "A1-160": [
    "Mienfoo",
    "Common"
  ],
  "A1-161": [
    "Mienshao",
    "Uncommon"
  ],
  "A1-162": [
    "Clobbopus",
    "Common"
  ],
  "A1-163": [
    "Grapploct",
    "Uncommon"
  ],
  "A1-164": [
    "Ekans",
    "Common"
  ],
  "A1-165": [
    "Arbok",
    "Uncommon"
  ],
  "A1-166": [
    "Nidoran\u2640",
    "Common"
  ],
  "A1-167": [
    "Nidorina",
    "Uncommon"
  ],
  "A1-168": [
    "Nidoqueen",
    "Rare"
  ],
  "A1-169": [
    "Nidoran\u2642",
    "Common"
  ],
  "A1-170": [
    "Nidorino",
    "Uncommon"
  ],
  "A1-171": [
    "Nidoking",
    "Rare"
  ],
  "A1-172": [
    "Zubat",
    "Common"
  ],
  "A1-173": [
    "Golbat",
    "Uncommon"
  ],
  "A1-174": [
    "Grimer",
    "Common"
  ],
  "A1-175": [
    "Muk",
    "Rare"
  ],
  "A1-176": [
    "Koffing",
    "Common"
  ],
  "A1-177": [
    "Weezing",
    "Rare"
  ],
  "A1-178": [
    "Mawile",
    "Common"
  ],
  "A1-179": [
    "Pawniard",
    "Common"
  ],
  "A1-180": [
    "Bisharp",
    "Uncommon"
  ],
  "A1-181": [
    "Meltan",
    "Common"
  ],
  "A1-182": [
    "Melmetal",
    "Rare"
  ],
  "A1-183": [
    "Dratini",
    "Common"
  ],
  "A1-184": [
    "Dragonair",
    "Uncommon"
  ],
  "A1-185": [
    "Dragonite",
    "Rare"
  ],
  "A1-186": [
    "Pidgey",
    "Common"
  ],
  "A1-187": [
    "Pidgeotto",
    "Common"
  ],
  "A1-188": [
    "Pidgeot",
    "Rare"
  ],
  "A1-189": [
    "Rattata",
    "Common"
  ],
  "A1-190": [
    "Raticate",
    "Common"
  ],
  "A1-191": [
    "Spearow",
    "Common"
  ],
  "A1-192": [
    "Fearow",
    "Common"
  ],
  "A1-193": [
    "Jigglypuff",
    "Common"
  ],
  "A1-194": [
    "Wigglytuff",
    "Common"
  ],
  "A1-195": [
    "Wigglytuff ex",
    "Double Rare"
  ],
  "A1-196": [
    "Meowth",
    "Common"
  ],
  "A1-197": [
    "Persian",
    "Uncommon"
  ],
  "A1-198": [
    "Farfetch'd",
    "Common"
  ],
  "A1-199": [
    "Doduo",
    "Common"
  ],
  "A1-200": [
    "Dodrio",
    "Uncommon"
  ],
  "A1-201": [
    "Lickitung",
    "Uncommon"
  ],
  "A1-202": [
    "Chansey",
    "Uncommon"
  ],
  "A1-203": [
    "Kangaskhan",
    "Rare"
  ],
  "A1-204": [
    "Tauros",
    "Uncommon"
  ],
  "A1-205": [
    "Ditto",
    "Rare"
  ],
  "A1-206": [
    "Eevee",
    "Common"
  ],
  "A1-207": [
    "Eevee",
    "Common"
  ],
  "A1-208": [
    "Eevee",
    "Common"
  ],
  "A1-209": [
    "Porygon",
    "Uncommon"
  ],
  "A1-210": [
    "Aerodactyl",
    "Rare"
  ],
  "A1-211": [
    "Snorlax",
    "Rare"
  ],
  "A1-212": [
    "Minccino",
    "Common"
  ],
  "A1-213": [
    "Cinccino",
    "Uncommon"
  ],
  "A1-214": [
    "Wooloo",
    "Common"
  ],
  "A1-215": [
    "Dubwool",
    "Common"
  ],
  "A1-216": [
    "Helix Fossil",
    "Uncommon"
  ],
  "A1-217": [
    "Dome Fossil",
    "Uncommon"
  ],
  "A1-218": [
    "Old Amber",
    "Uncommon"
  ],
  "A1-219": [
    "Erika",
    "Uncommon"
  ],
  "A1-220": [
    "Misty",
    "Uncommon"
  ],
  "A1-221": [
    "Blaine",
    "Uncommon"
  ],
  "A1-222": [
    "Koga",
    "Uncommon"
  ],
  "A1-223": [
    "Giovanni",
    "Uncommon"
  ],
  "A1-224": [
    "Brock",
    "Uncommon"
  ],
  "A1-225": [
    "Sabrina",
    "Uncommon"
  ],
  "A1-226": [
    "Lt. Surge",
    "Uncommon"
  ],
  "A1-227": [
    "Bulbasaur",
    "Art Rare"
  ],
  "A1-228": [
    "Gloom",
    "Art Rare"
  ],
  "A1-229": [
    "Pinsir",
    "Art Rare"
  ],
  "A1-230": [
    "Charmander",
    "Art Rare"
  ],
  "A1-231": [
    "Rapidash",
    "Art Rare"
  ],
  "A1-232": [
    "Squirtle",
    "Art Rare"
  ],
  "A1-233": [
    "Gyarados",
    "Art Rare"
  ],
  "A1-234": [
    "Lapras",
    "Art Rare"
  ],
  "A1-235": [
    "Electrode",
    "Art Rare"
  ],
  "A1-236": [
    "Alakazam",
    "Art Rare"
  ],
  "A1-237": [
    "Slowpoke",
    "Art Rare"
  ],
  "A1-238": [
    "Diglett",
    "Art Rare"
  ],
  "A1-239": [
    "Cubone",
    "Art Rare"
  ],
  "A1-240": [
    "Nidoqueen",
    "Art Rare"
  ],
  "A1-241": [
    "Nidoking",
    "Art Rare"
  ],
  "A1-242": [
    "Golbat",
    "Art Rare"
  ],
  "A1-243": [
    "Weezing",
    "Art Rare"
  ],
  "A1-244": [
    "Dragonite",
    "Art Rare"
  ],
  "A1-245": [
    "Pidgeot",
    "Art Rare"
  ],
  "A1-246": [
    "Meowth",
    "Art Rare"
  ],
  "A1-247": [
    "Ditto",
    "Art Rare"
  ],
  "A1-248": [
    "Eevee",
    "Art Rare"
  ],
  "A1-249": [
    "Porygon",
    "Art Rare"
  ],
  "A1-250": [
    "Snorlax",
    "Art Rare"
  ],
  "A1a-001": [
    "Exeggcute",
    "Common"
  ],
  "A1a-002": [
    "Exeggutor",
    "Uncommon"
  ],
  "A1a-003": [
    "Celebi ex",
    "Double Rare"
  ],
  "A1a-004": [
    "Snivy",
    "Common"
  ],
  "A1a-005": [
    "Servine",
    "Uncommon"
  ],
  "A1a-006": [
    "Serperior",
    "Rare"
  ],
  "A1a-007": [
    "Morelull",
    "Common"
  ],
  "A1a-008": [
    "Shiinotic",
    "Uncommon"
  ],
  "A1a-009": [
    "Dhelmise",
    "Uncommon"
  ],
  "A1a-010": [
    "Ponyta",
    "Common"
  ],
  "A1a-011": [
    "Rapidash",
    "Uncommon"
  ],
  "A1a-012": [
    "Magmar",
    "Uncommon"
  ],
  "A1a-013": [
    "Larvesta",
    "Common"
  ],
  "A1a-014": [
    "Volcarona",
    "Rare"
  ],
  "A1a-015": [
    "Salandit",
    "Common"
  ],
  "A1a-016": [
    "Salazzle",
    "Common"
  ],
  "A1a-017": [
    "Magikarp",
    "Common"
  ],
  "A1a-018": [
    "Gyarados ex",
    "Double Rare"
  ],
  "A1a-019": [
    "Vaporeon",
    "Rare"
  ],
  "A1a-020": [
    "Finneon",
    "Common"
  ],
  "A1a-021": [
    "Lumineon",
    "Uncommon"
  ],
  "A1a-022": [
    "Chewtle",
    "Common"
  ],
  "A1a-023": [
    "Drednaw",
    "Uncommon"
  ],
  "A1a-024": [
    "Cramorant",
    "Common"
  ],
  "A1a-025": [
    "Pikachu",
    "Common"
  ],
  "A1a-026": [
    "Raichu",
    "Rare"
  ],
  "A1a-027": [
    "Electabuzz",
    "Uncommon"
  ],
  "A1a-028": [
    "Joltik",
    "Common"
  ],
  "A1a-029": [
    "Galvantula",
    "Uncommon"
  ],
  "A1a-030": [
    "Dedenne",
    "Common"
  ],
  "A1a-031": [
    "Mew",
    "Rare"
  ],
  "A1a-032": [
    "Mew ex",
    "Double Rare"
  ],
  "A1a-033": [
    "Sigilyph",
    "Uncommon"
  ],
  "A1a-034": [
    "Elgyem",
    "Common"
  ],
  "A1a-035": [
    "Beheeyem",
    "Uncommon"
  ],
  "A1a-036": [
    "Flab\u00e9b\u00e9",
    "Common"
  ],
  "A1a-037": [
    "Floette",
    "Common"
  ],
  "A1a-038": [
    "Florges",
    "Uncommon"
  ],
  "A1a-039": [
    "Swirlix",
    "Common"
  ],
  "A1a-040": [
    "Slurpuff",
    "Common"
  ],
  "A1a-041": [
    "Mankey",
    "Common"
  ],
  "A1a-042": [
    "Primeape",
    "Common"
  ],
  "A1a-043": [
    "Geodude",
    "Common"
  ],
  "A1a-044": [
    "Graveler",
    "Uncommon"
  ],
  "A1a-045": [
    "Golem",
    "Rare"
  ],
  "A1a-046": [
    "Aerodactyl ex",
    "Double Rare"
  ],
  "A1a-047": [
    "Marshadow",
    "Rare"
  ],
  "A1a-048": [
    "Stonjourner",
    "Uncommon"
  ],
  "A1a-049": [
    "Koffing",
    "Common"
  ],
  "A1a-050": [
    "Weezing",
    "Uncommon"
  ],
  "A1a-051": [
    "Purrloin",
    "Common"
  ],
  "A1a-052": [
    "Liepard",
    "Common"
  ],
  "A1a-053": [
    "Venipede",
    "Common"
  ],
  "A1a-054": [
    "Whirlipede",
    "Common"
  ],
  "A1a-055": [
    "Scolipede",
    "Uncommon"
  ],
  "A1a-056": [
    "Druddigon",
    "Uncommon"
  ],
  "A1a-057": [
    "Pidgey",
    "Common"
  ],
  "A1a-058": [
    "Pidgeotto",
    "Common"
  ],
  "A1a-059": [
    "Pidgeot ex",
    "Double Rare"
  ],
  "A1a-060": [
    "Tauros",
    "Rare"
  ],
  "A1a-061": [
    "Eevee",
    "Common"
  ],
  "A1a-062": [
    "Chatot",
    "Common"
  ],
  "A1a-063": [
    "Old Amber",
    "Uncommon"
  ],
  "A1a-064": [
    "Pok\u00e9mon Flute",
    "Uncommon"
  ],
  "A1a-065": [
    "Mythical Slab",
    "Uncommon"
  ],
  "A1a-066": [
    "Budding Expeditioner",
    "Uncommon"
  ],
  "A1a-067": [
    "Blue",
    "Uncommon"
  ],
  "A1a-068": [
    "Leaf",
    "Uncommon"
  ],
  "A1a-069": [
    "Exeggutor",
    "Art Rare"
  ],
  "A1a-070": [
    "Serperior",
    "Art Rare"
  ],
  "A1a-071": [
    "Salandit",
    "Art Rare"
  ],
  "A1a-072": [
    "Vaporeon",
    "Art Rare"
  ],
  "A1a-073": [
    "Dedenne",
    "Art Rare"
  ],
  "A1a-074": [
    "Marshadow",
    "Art Rare"
  ],
  "A2-001": [
    "Oddish",
    "Common"
  ],
  "A2-002": [
    "Gloom",
    "Common"
  ],
  "A2-003": [
    "Bellossom",
    "Uncommon"
  ],
  "A2-004": [
    "Tangela",
    "Common"
  ],
  "A2-005": [
    "Tangrowth",
    "Uncommon"
  ],
  "A2-006": [
    "Yanma",
    "Common"
  ],
  "A2-007": [
    "Yanmega ex",
    "Double Rare"
  ],
  "A2-008": [
    "Roselia",
    "Common"
  ],
  "A2-009": [
    "Roserade",
    "Uncommon"
  ],
  "A2-010": [
    "Turtwig",
    "Common"
  ],
  "A2-011": [
    "Grotle",
    "Uncommon"
  ],
  "A2-012": [
    "Torterra",
    "Rare"
  ],
  "A2-013": [
    "Kricketot",
    "Common"
  ],
  "A2-014": [
    "Kricketune",
    "Common"
  ],
  "A2-015": [
    "Burmy",
    "Common"
  ],
  "A2-016": [
    "Wormadam",
    "Common"
  ],
  "A2-017": [
    "Combee",
    "Common"
  ],
  "A2-018": [
    "Vespiquen",
    "Uncommon"
  ],
  "A2-019": [
    "Carnivine",
    "Uncommon"
  ],
  "A2-020": [
    "Leafeon",
    "Rare"
  ],
  "A2-021": [
    "Mow Rotom",
    "Common"
  ],
  "A2-022": [
    "Shaymin",
    "Rare"
  ],
  "A2-023": [
    "Magmar",
    "Common"
  ],
  "A2-024": [
    "Magmortar",
    "Rare"
  ],
  "A2-025": [
    "Slugma",
    "Common"
  ],
  "A2-026": [
    "Magcargo",
    "Uncommon"
  ],
  "A2-027": [
    "Chimchar",
    "Common"
  ],
  "A2-028": [
    "Monferno",
    "Uncommon"
  ],
  "A2-029": [
    "Infernape ex",
    "Double Rare"
  ],
  "A2-030": [
    "Heat Rotom",
    "Common"
  ],
  "A2-031": [
    "Swinub",
    "Common"
  ],
  "A2-032": [
    "Piloswine",
    "Uncommon"
  ],
  "A2-033": [
    "Mamoswine",
    "Rare"
  ],
  "A2-034": [
    "Regice",
    "Uncommon"
  ],
  "A2-035": [
    "Piplup",
    "Common"
  ],
  "A2-036": [
    "Prinplup",
    "Uncommon"
  ],
  "A2-037": [
    "Empoleon",
    "Rare"
  ],
  "A2-038": [
    "Buizel",
    "Common"
  ],
  "A2-039": [
    "Floatzel",
    "Uncommon"
  ],
  "A2-040": [
    "Shellos",
    "Common"
  ],
  "A2-041": [
    "Gastrodon",
    "Uncommon"
  ],
  "A2-042": [
    "Finneon",
    "Common"
  ],
  "A2-043": [
    "Lumineon",
    "Uncommon"
  ],
  "A2-044": [
    "Snover",
    "Common"
  ],
  "A2-045": [
    "Abomasnow",
    "Uncommon"
  ],
  "A2-046": [
    "Glaceon",
    "Rare"
  ],
  "A2-047": [
    "Wash Rotom",
    "Common"
  ],
  "A2-048": [
    "Frost Rotom",
    "Common"
  ],
  "A2-049": [
    "Palkia ex",
    "Double Rare"
  ],
  "A2-050": [
    "Manaphy",
    "Uncommon"
  ],
  "A2-051": [
    "Magnemite",
    "Common"
  ],
  "A2-052": [
    "Magneton",
    "Uncommon"
  ],
  "A2-053": [
    "Magnezone",
    "Rare"
  ],
  "A2-054": [
    "Voltorb",
    "Common"
  ],
  "A2-055": [
    "Electrode",
    "Uncommon"
  ],
  "A2-056": [
    "Electabuzz",
    "Common"
  ],
  "A2-057": [
    "Electivire",
    "Rare"
  ],
  "A2-058": [
    "Shinx",
    "Common"
  ],
  "A2-059": [
    "Luxio",
    "Uncommon"
  ],
  "A2-060": [
    "Luxray",
    "Rare"
  ],
  "A2-061": [
    "Pachirisu ex",
    "Double Rare"
  ],
  "A2-062": [
    "Rotom",
    "Common"
  ],
  "A2-063": [
    "Togepi",
    "Common"
  ],
  "A2-064": [
    "Togetic",
    "Uncommon"
  ],
  "A2-065": [
    "Togekiss",
    "Rare"
  ],
  "A2-066": [
    "Misdreavus",
    "Common"
  ],
  "A2-067": [
    "Mismagius ex",
    "Double Rare"
  ],
  "A2-068": [
    "Ralts",
    "Common"
  ],
  "A2-069": [
    "Kirlia",
    "Common"
  ],
  "A2-070": [
    "Duskull",
    "Common"
  ],
  "A2-071": [
    "Dusclops",
    "Uncommon"
  ],
  "A2-072": [
    "Dusknoir",
    "Rare"
  ],
  "A2-073": [
    "Drifloon",
    "Common"
  ],
  "A2-074": [
    "Drifblim",
    "Uncommon"
  ],
  "A2-075": [
    "Uxie",
    "Uncommon"
  ],
  "A2-076": [
    "Mesprit",
    "Rare"
  ],
  "A2-077": [
    "Azelf",
    "Uncommon"
  ],
  "A2-078": [
    "Giratina",
    "Rare"
  ],
  "A2-079": [
    "Cresselia",
    "Rare"
  ],
  "A2-080": [
    "Rhyhorn",
    "Common"
  ],
  "A2-081": [
    "Rhydon",
    "Uncommon"
  ],
  "A2-082": [
    "Rhyperior",
    "Rare"
  ],
  "A2-083": [
    "Gligar",
    "Common"
  ],
  "A2-084": [
    "Gliscor",
    "Uncommon"
  ],
  "A2-085": [
    "Hitmontop",
    "Common"
  ],
  "A2-086": [
    "Nosepass",
    "Common"
  ],
  "A2-087": [
    "Regirock",
    "Uncommon"
  ],
  "A2-088": [
    "Cranidos",
    "Uncommon"
  ],
  "A2-089": [
    "Rampardos",
    "Rare"
  ],
  "A2-090": [
    "Wormadam",
    "Common"
  ],
  "A2-091": [
    "Riolu",
    "Common"
  ],
  "A2-092": [
    "Lucario",
    "Rare"
  ],
  "A2-093": [
    "Hippopotas",
    "Common"
  ],
  "A2-094": [
    "Hippowdon",
    "Uncommon"
  ],
  "A2-095": [
    "Gallade ex",
    "Double Rare"
  ],
  "A2-096": [
    "Murkrow",
    "Common"
  ],
  "A2-097": [
    "Honchkrow",
    "Uncommon"
  ],
  "A2-098": [
    "Sneasel",
    "Common"
  ],
  "A2-099": [
    "Weavile ex",
    "Double Rare"
  ],
  "A2-100": [
    "Poochyena",
    "Common"
  ],
  "A2-101": [
    "Mightyena",
    "Uncommon"
  ],
  "A2-102": [
    "Stunky",
    "Common"
  ],
  "A2-103": [
    "Skuntank",
    "Uncommon"
  ],
  "A2-104": [
    "Spiritomb",
    "Uncommon"
  ],
  "A2-105": [
    "Skorupi",
    "Common"
  ],
  "A2-106": [
    "Drapion",
    "Uncommon"
  ],
  "A2-107": [
    "Croagunk",
    "Common"
  ],
  "A2-108": [
    "Toxicroak",
    "Uncommon"
  ],
  "A2-109": [
    "Darkrai",
    "Rare"
  ],
  "A2-110": [
    "Darkrai ex",
    "Double Rare"
  ],
  "A2-111": [
    "Skarmory",
    "Uncommon"
  ],
  "A2-112": [
    "Registeel",
    "Uncommon"
  ],
  "A2-113": [
    "Shieldon",
    "Uncommon"
  ],
  "A2-114": [
    "Bastiodon",
    "Rare"
  ],
  "A2-115": [
    "Wormadam",
    "Common"
  ],
  "A2-116": [
    "Bronzor",
    "Common"
  ],
  "A2-117": [
    "Bronzong",
    "Uncommon"
  ],
  "A2-118": [
    "Probopass",
    "Uncommon"
  ],
  "A2-119": [
    "Dialga ex",
    "Double Rare"
  ],
  "A2-120": [
    "Heatran",
    "Rare"
  ],
  "A2-121": [
    "Gible",
    "Common"
  ],
  "A2-122": [
    "Gabite",
    "Uncommon"
  ],
  "A2-123": [
    "Garchomp",
    "Rare"
  ],
  "A2-124": [
    "Lickitung",
    "Common"
  ],
  "A2-125": [
    "Lickilicky ex",
    "Double Rare"
  ],
  "A2-126": [
    "Eevee",
    "Common"
  ],
  "A2-127": [
    "Porygon",
    "Common"
  ],
  "A2-128": [
    "Porygon2",
    "Uncommon"
  ],
  "A2-129": [
    "Porygon-Z",
    "Rare"
  ],
  "A2-130": [
    "Aipom",
    "Common"
  ],
  "A2-131": [
    "Ambipom",
    "Common"
  ],
  "A2-132": [
    "Starly",
    "Common"
  ],
  "A2-133": [
    "Staravia",
    "Common"
  ],
  "A2-134": [
    "Staraptor",
    "Uncommon"
  ],
  "A2-135": [
    "Bidoof",
    "Common"
  ],
  "A2-136": [
    "Bibarel",
    "Common"
  ],
  "A2-137": [
    "Buneary",
    "Common"
  ],
  "A2-138": [
    "Lopunny",
    "Common"
  ],
  "A2-139": [
    "Glameow",
    "Common"
  ],
  "A2-140": [
    "Purugly",
    "Uncommon"
  ],
  "A2-141": [
    "Chatot",
    "Common"
  ],
  "A2-142": [
    "Fan Rotom",
    "Common"
  ],
  "A2-143": [
    "Regigigas",
    "Rare"
  ],
  "A2-144": [
    "Skull Fossil",
    "Common"
  ],
  "A2-145": [
    "Armor Fossil",
    "Common"
  ],
  "A2-146": [
    "Pok\u00e9mon Communication",
    "Uncommon"
  ],
  "A2-147": [
    "Giant Cape",
    "Uncommon"
  ],
  "A2-148": [
    "Rocky Helmet",
    "Uncommon"
  ],
  "A2-149": [
    "Lum Berry",
    "Uncommon"
  ],
  "A2-150": [
    "Cyrus",
    "Uncommon"
  ],
  "A2-151": [
    "Team Galactic Grunt",
    "Uncommon"
  ],
  "A2-152": [
    "Cynthia",
    "Uncommon"
  ],
  "A2-153": [
    "Volkner",
    "Uncommon"
  ],
  "A2-154": [
    "Dawn",
    "Uncommon"
  ],
  "A2-155": [
    "Mars",
    "Uncommon"
  ],
  "A2-156": [
    "Tangrowth",
    "Art Rare"
  ],
  "A2-157": [
    "Combee",
    "Art Rare"
  ],
  "A2-158": [
    "Carnivine",
    "Art Rare"
  ],
  "A2-159": [
    "Shaymin",
    "Art Rare"
  ],
  "A2-160": [
    "Mamoswine",
    "Art Rare"
  ],
  "A2-161": [
    "Gastrodon",
    "Art Rare"
  ],
  "A2-162": [
    "Manaphy",
    "Art Rare"
  ],
  "A2-163": [
    "Shinx",
    "Art Rare"
  ],
  "A2-164": [
    "Rotom",
    "Art Rare"
  ],
  "A2-165": [
    "Drifloon",
    "Art Rare"
  ],
  "A2-166": [
    "Mesprit",
    "Art Rare"
  ],
  "A2-167": [
    "Giratina",
    "Art Rare"
  ],
  "A2-168": [
    "Cresselia",
    "Art Rare"
  ],
  "A2-169": [
    "Rhyperior",
    "Art Rare"
  ],
  "A2-170": [
    "Lucario",
    "Art Rare"
  ],
  "A2-171": [
    "Hippopotas",
    "Art Rare"
  ],
  "A2-172": [
    "Spiritomb",
    "Art Rare"
  ],
  "A2-173": [
    "Croagunk",
    "Art Rare"
  ],
  "A2-174": [
    "Heatran",
    "Art Rare"
  ],
  "A2-175": [
    "Garchomp",
    "Art Rare"
  ],
  "A2-176": [
    "Staraptor",
    "Art Rare"
  ],
  "A2-177": [
    "Bidoof",
    "Art Rare"
  ],
  "A2-178": [
    "Glameow",
    "Art Rare"
  ],
  "A2-179": [
    "Regigigas",
    "Art Rare"
  ]
}